typing_game/__init__.py
typing_game/cli.py
typing_game/config.py
typing_game/controllers.py
typing_game/core.py
typing_game/views.py
typing_game/_static/home.jpg
typing_game/api/__init__.py
typing_game/api/generics.py
typing_game/api/utils.py
typing_game/api/mixins/__init__.py
typing_game/api/mixins/colors.py
typing_game/api/mixins/typings.py
typing_game/api/mixins/font/__init__.py
typing_game/api/mixins/font/model.py
typing_game/api/mixins/font/name.py
typing_game-0.3.1.dist-info/LICENSE
typing_game-0.3.1.dist-info/METADATA
typing_game-0.3.1.dist-info/WHEEL
typing_game-0.3.1.dist-info/entry_points.txt
typing_game-0.3.1.dist-info/top_level.txt
typing_game-0.3.1.dist-info/RECORD
