Metadata-Version: 2.1
Name: typing-game
Version: 0.3.1
Summary: Typing Game
Home-page: https://github.com/CarsonSlovoka/typing-game/tree/master
Author: Carson
Author-email: jackparadise520a@gmail.com
License: MIT
Download-URL: https://github.com/CarsonSlovoka/typing-game/tree/master/tarball/v0.3.1
Keywords: typing,game,pygame,pygame-menu
Platform: UNKNOWN
Classifier: Topic :: Education
Classifier: Topic :: Games/Entertainment
Classifier: Topic :: Software Development
Classifier: Typing :: Typed
Classifier: Topic :: Utilities
Classifier: Natural Language :: Chinese (Traditional)
Classifier: Natural Language :: English
Classifier: Operating System :: Microsoft
Classifier: Development Status :: 3 - Alpha
Classifier: License :: OSI Approved :: MIT License
Classifier: Programming Language :: Python :: 3 :: Only
Requires-Python: >=3.6.2,
Requires-Dist: pygame
Requires-Dist: pygame-menu
